argparse_hparams/__init__.py
argparse_hparams/parsing.py
argparse_hparams/utils.py
argparse_hparams/version.py
argparse_hparams-0.0.1.dev20220103160002.dist-info/LICENSE
argparse_hparams-0.0.1.dev20220103160002.dist-info/METADATA
argparse_hparams-0.0.1.dev20220103160002.dist-info/WHEEL
argparse_hparams-0.0.1.dev20220103160002.dist-info/top_level.txt
argparse_hparams-0.0.1.dev20220103160002.dist-info/RECORD
