Metadata-Version: 2.1
Name: argparse-hparams
Version: 0.0.1.dev20220103160002
Summary: An HParams implementation with argparse.
Home-page: https://github.com/enhuiz/argparse-hparams
Author: enhuiz
Author-email: niuzhe.nz@outlook.com
License: UNKNOWN
Platform: UNKNOWN
Requires-Python: >=3.9.0
License-File: LICENSE
Requires-Dist: pyyaml
